ephem/__init__.py
ephem/cli.py
ephem/config.py
ephem/constants.py
ephem/db.py
ephem/yaml_sync.py
ephem/commands/cal.py
ephem/commands/cast.py
ephem/commands/data.py
ephem/commands/now.py
ephem/display/__init__.py
ephem/display/chart.py
ephem/display/month.py
ephem/sweph/__init__.py
ephem/sweph/angles.py
ephem/sweph/ayanamsas.py
ephem/sweph/core.py
ephem/sweph/houses.py
ephem/sweph/julian.py
ephem/sweph/planets.py
ephem/utils/__init__.py
ephem/utils/locale.py
ephem/utils/signs.py
ephem/utils/timezone.py
ephem/utils/year.py
ephem_cli-2.0.6.dist-info/licenses/LICENSE
ephem_cli-2.0.6.dist-info/METADATA
ephem_cli-2.0.6.dist-info/WHEEL
ephem_cli-2.0.6.dist-info/entry_points.txt
ephem_cli-2.0.6.dist-info/top_level.txt
ephem_cli-2.0.6.dist-info/RECORD
