Metadata-Version: 2.4
Name: ephem-cli
Version: 2.0.6
Summary: A minimal and configurable astrology CLI
Author-email: sailorfe <sailorf@proton.me>
License-Expression: AGPL-3.0-or-later
Project-URL: Repository, https://codeberg.org/sailorfe/ephem
Keywords: astrology,horoscope
Classifier: Development Status :: 5 - Production/Stable
Classifier: Intended Audience :: End Users/Desktop
Classifier: Intended Audience :: Science/Research
Classifier: Intended Audience :: Religion
Classifier: Topic :: Utilities
Classifier: Topic :: Scientific/Engineering
Classifier: Topic :: Religion
Classifier: Programming Language :: Python :: 3
Classifier: Programming Language :: Python :: 3.13
Requires-Python: <4.0,>=3.8
License-File: LICENSE
Requires-Dist: pyswisseph
Requires-Dist: pyyaml
Requires-Dist: rich
Requires-Dist: tomli_w
Dynamic: license-file
